MANIFEST.in
NEWS.md
README.md
setup.py
fixxd/__init__.py
fixxd/cli.py
fixxd/config.py
fixxd/core.py
fixxd/device.py
fixxd/prepare.py
fixxd/simulator.py
fixxd/utils.py
fixxd.egg-info/PKG-INFO
fixxd.egg-info/SOURCES.txt
fixxd.egg-info/dependency_links.txt
fixxd.egg-info/entry_points.txt
fixxd.egg-info/not-zip-safe
fixxd.egg-info/requires.txt
fixxd.egg-info/top_level.txt