Metadata-Version: 1.0
Name: fixxd
Version: 0.2.1
Summary: iOS UIAutomation tests launcher
Home-page: https://github.com/Stupeflix/fixxd
Author: Francescu
Author-email: UNKNOWN
License: MIT
Keywords: ios,uiautomation,tests,instruments,ui,automation
Platform: UNKNOWN
